supertriplets/__init__.py
supertriplets/dataset.py
supertriplets/distance.py
supertriplets/encoder.py
supertriplets/evaluate.py
supertriplets/index.py
supertriplets/loss.py
supertriplets/sample.py
supertriplets/utils.py
supertriplets/models/__init__.py
supertriplets/models/_loader.py
supertriplets/models/_registry.py
supertriplets/models/language.py
supertriplets/models/multimodal.py
supertriplets/models/vision.py
supertriplets-1.0.6.dist-info/LICENSE.txt
supertriplets-1.0.6.dist-info/METADATA
supertriplets-1.0.6.dist-info/WHEEL
supertriplets-1.0.6.dist-info/top_level.txt
supertriplets-1.0.6.dist-info/RECORD
