Metadata-Version: 2.1
Name: supertriplets
Version: 1.0.6
Summary: Torch Multimodal Supervised Triplet Learning Toolbox
Author-email: Gabriel Tardochi Salles <ga.tardochisalles@gmail.com>
Maintainer-email: Gabriel Tardochi Salles <ga.tardochisalles@gmail.com>
License: MIT License
Project-URL: Homepage, https://github.com/gabrieltardochi/supertriplets
Project-URL: Repository, https://github.com/gabrieltardochi/supertriplets
Project-URL: Changelog, https://github.com/gabrieltardochi/supertriplets/blob/main/CHANGELOG.md
Keywords: data-science,contrastive-learning,triplet-learning,online-triplet-learning,natural-language-processing,computer-vision,artificial-intelligence,machine-learning,deep-learning,transformers,nlp,cv
Classifier: Intended Audience :: Science/Research
Classifier: Topic :: Scientific/Engineering :: Artificial Intelligence
Classifier: Development Status :: 5 - Production/Stable
Classifier: Programming Language :: Python :: 3.8
Classifier: Programming Language :: Python :: 3.9
Classifier: Programming Language :: Python :: 3.10
Classifier: Programming Language :: Python :: 3.11
Classifier: Programming Language :: Python :: 3.12
Classifier: Programming Language :: Python :: 3.13
Requires-Python: >=3.8
License-File: LICENSE.txt
Requires-Dist: pandas
Requires-Dist: numpy
Requires-Dist: Pillow
Requires-Dist: torch
Requires-Dist: timm
Requires-Dist: torchvision
Requires-Dist: transformers
Requires-Dist: sentence-transformers
Requires-Dist: scikit-learn
Requires-Dist: faiss-gpu
Provides-Extra: dev
Requires-Dist: pre-commit ; extra == 'dev'
Requires-Dist: ruff ; extra == 'dev'
Requires-Dist: black ; extra == 'dev'
Requires-Dist: pytest ; extra == 'dev'
Requires-Dist: pytest-cov ; extra == 'dev'
